understory/apps/websub_endpoint/__init__.py
understory/apps/websub_endpoint/templates/__init__.py
understory/apps/websub_endpoint/templates/hub.html
understory/apps/websub_endpoint/templates/received/__init__.py
understory/apps/websub_endpoint/templates/sent/__init__.py
understory/apps/websub_endpoint/templates/sent/subscription.html
understory/apps/websub_endpoint/templates/sent/subscription_requested.html
understory_websub_endpoint-0.0.4.dist-info/entry_points.txt
understory_websub_endpoint-0.0.4.dist-info/LICENSE
understory_websub_endpoint-0.0.4.dist-info/WHEEL
understory_websub_endpoint-0.0.4.dist-info/METADATA
understory_websub_endpoint-0.0.4.dist-info/RECORD
